modulink/__init__.py
modulink/__main__.py
modulink/_fuzzy_imports.py
modulink/chain.py
modulink/cli_visualize.py
modulink/context.py
modulink/docs.py
modulink/graphviz_utils.py
modulink/link.py
modulink/listeners.py
modulink/middleware.py
modulink/modulink_doc.py
modulink_py-4.0.3.dist-info/licenses/LICENSE
modulink_py-4.0.3.dist-info/METADATA
modulink_py-4.0.3.dist-info/WHEEL
modulink_py-4.0.3.dist-info/top_level.txt
modulink_py-4.0.3.dist-info/RECORD
