Metadata-Version: 2.4
Name: modulink-py
Version: 4.0.3
Summary: A Python library for building modular applications with unified triggers
Author-email: Orchestrate LLC <joshua@orchestrate.solutions>
Maintainer-email: Orchestrate LLC <joshua@orchestrate.solutions>
License-Expression: Apache-2.0
Project-URL: Homepage, https://github.com/orchestrate-solutions/modulink-py
Project-URL: Repository, https://github.com/orchestrate-solutions/modulink-py
Project-URL: Issues, https://github.com/orchestrate-solutions/modulink-py/issues
Project-URL: Documentation, https://github.com/orchestrate-solutions/modulink-py#readme
Keywords: modular,applications,triggers,fastapi,automation,scheduling
Classifier: Development Status :: 4 - Beta
Classifier: Intended Audience :: Developers
Classifier: Operating System :: OS Independent
Classifier: Programming Language :: Python :: 3
Classifier: Programming Language :: Python :: 3.8
Classifier: Programming Language :: Python :: 3.9
Classifier: Programming Language :: Python :: 3.10
Classifier: Programming Language :: Python :: 3.11
Classifier: Programming Language :: Python :: 3.12
Classifier: Programming Language :: Python :: 3.13
Classifier: Topic :: Software Development :: Libraries :: Python Modules
Classifier: Topic :: Internet :: WWW/HTTP :: HTTP Servers
Classifier: Topic :: System :: Systems Administration
Requires-Python: >=3.8
License-File: LICENSE
Requires-Dist: fastapi>=0.104.0
Requires-Dist: uvicorn>=0.24.0
Requires-Dist: apscheduler>=3.10.0
Requires-Dist: click>=8.1.0
Requires-Dist: pydantic>=2.5.0
Requires-Dist: typing-extensions>=4.8.0
Provides-Extra: dev
Requires-Dist: flake8>=6.0.0; extra == "dev"
Requires-Dist: black>=23.0.0; extra == "dev"
Requires-Dist: isort>=5.12.0; extra == "dev"
Requires-Dist: pytest>=7.4.0; extra == "dev"
Requires-Dist: pytest-cov>=4.1.0; extra == "dev"
Requires-Dist: pytest-asyncio>=0.21.0; extra == "dev"
Requires-Dist: pytest-mock>=3.10.0; extra == "dev"
Requires-Dist: mypy>=1.0.0; extra == "dev"
Requires-Dist: pre-commit>=3.0.0; extra == "dev"
Dynamic: license-file
